{
  "date": "2026-07-07",
  "period": "daily",
  "data_source": "sp_api",
  "source": "SP-API pipeline: Orders + Inventory + Catalog + Reports (GET_SALES_AND_TRAFFIC_REPORT) + Finances",
  "status": "Composed automatically by amazon_api/build_sc_data.py",
  "timestamp": "2026-07-07T17:32:18.267583Z",
  "highlights": {
    "revenue_7d": "7-day revenue $1279.64 across 14 orders (44 units).",
    "sessions_7d": "7-day sessions 151, CVR 32.45%.",
    "fountain_cover": "Fountain days of cover (7d velocity): 56.",
    "filters_cover": "Filter days of cover (7d velocity): 84."
  },
  "business_reports": {
    "date_range": "2026-06-29 to 2026-07-06",
    "period_days": 7,
    "_data_source": "sp_api_reports",
    "_note": "Pulled via Reports API: GET_SALES_AND_TRAFFIC_REPORT",
    "units_sold": 49,
    "revenue": 1429.61,
    "sessions_total": 151,
    "page_views_total": 210,
    "cvr_percent": 32.45,
    "per_asin": {
      "B0DJHQVJYF": {
        "sessions": 135,
        "sessions_b2b": 3,
        "page_views": 191,
        "page_views_b2b": 4,
        "browser_sessions": 43,
        "mobile_app_sessions": 92,
        "units": 39,
        "ordered_product_sales": 1229.61,
        "total_order_items": 11,
        "cvr_pct": 28.89,
        "buy_box_pct_avg": 98.16
      },
      "B0FWXJ1GKT": {
        "sessions": 13,
        "sessions_b2b": 0,
        "page_views": 16,
        "page_views_b2b": 0,
        "browser_sessions": 4,
        "mobile_app_sessions": 9,
        "units": 10,
        "ordered_product_sales": 200.0,
        "total_order_items": 8,
        "cvr_pct": 76.92,
        "buy_box_pct_avg": 100.0
      },
      "B0GMDM6CG2": {
        "sessions": 3,
        "sessions_b2b": 0,
        "page_views": 3,
        "page_views_b2b": 0,
        "browser_sessions": 1,
        "mobile_app_sessions": 2,
        "units": 0,
        "ordered_product_sales": 0.0,
        "total_order_items": 0,
        "cvr_pct": 0.0,
        "buy_box_pct_avg": 33.33
      }
    },
    "_all_asins": {
      "B0DJHQVJYF": {
        "sessions": 135,
        "sessions_b2b": 3,
        "page_views": 191,
        "page_views_b2b": 4,
        "browser_sessions": 43,
        "mobile_app_sessions": 92,
        "units": 39,
        "ordered_product_sales": 1229.61,
        "total_order_items": 11,
        "cvr_pct": 28.89,
        "buy_box_pct_avg": 98.16
      },
      "B0FWXJ1GKT": {
        "sessions": 13,
        "sessions_b2b": 0,
        "page_views": 16,
        "page_views_b2b": 0,
        "browser_sessions": 4,
        "mobile_app_sessions": 9,
        "units": 10,
        "ordered_product_sales": 200.0,
        "total_order_items": 8,
        "cvr_pct": 76.92,
        "buy_box_pct_avg": 100.0
      },
      "B0GMDM6CG2": {
        "sessions": 3,
        "sessions_b2b": 0,
        "page_views": 3,
        "page_views_b2b": 0,
        "browser_sessions": 1,
        "mobile_app_sessions": 2,
        "units": 0,
        "ordered_product_sales": 0.0,
        "total_order_items": 0,
        "cvr_pct": 0.0,
        "buy_box_pct_avg": 33.33
      }
    }
  },
  "business_reports_30day": {
    "date_range": "2026-06-06 to 2026-07-06",
    "period_days": 30,
    "_data_source": "sp_api_reports",
    "_note": "Pulled via Reports API: GET_SALES_AND_TRAFFIC_REPORT",
    "units_sold": 82,
    "revenue": 2531.76,
    "sessions_total": 597,
    "page_views_total": 822,
    "cvr_percent": 13.74,
    "per_asin": {
      "B0DJHQVJYF": {
        "sessions": 553,
        "sessions_b2b": 5,
        "page_views": 765,
        "page_views_b2b": 6,
        "browser_sessions": 151,
        "mobile_app_sessions": 402,
        "units": 54,
        "ordered_product_sales": 1973.96,
        "total_order_items": 25,
        "cvr_pct": 9.76,
        "buy_box_pct_avg": 98.32
      },
      "B0FWXJ1GKT": {
        "sessions": 35,
        "sessions_b2b": 0,
        "page_views": 42,
        "page_views_b2b": 0,
        "browser_sessions": 10,
        "mobile_app_sessions": 25,
        "units": 28,
        "ordered_product_sales": 557.8,
        "total_order_items": 23,
        "cvr_pct": 80.0,
        "buy_box_pct_avg": 100.0
      },
      "B0GMDM6CG2": {
        "sessions": 9,
        "sessions_b2b": 0,
        "page_views": 15,
        "page_views_b2b": 0,
        "browser_sessions": 1,
        "mobile_app_sessions": 8,
        "units": 0,
        "ordered_product_sales": 0.0,
        "total_order_items": 0,
        "cvr_pct": 0.0,
        "buy_box_pct_avg": 75.0
      }
    },
    "_all_asins": {
      "B0DJHQVJYF": {
        "sessions": 553,
        "sessions_b2b": 5,
        "page_views": 765,
        "page_views_b2b": 6,
        "browser_sessions": 151,
        "mobile_app_sessions": 402,
        "units": 54,
        "ordered_product_sales": 1973.96,
        "total_order_items": 25,
        "cvr_pct": 9.76,
        "buy_box_pct_avg": 98.32
      },
      "B0FWXJ1GKT": {
        "sessions": 35,
        "sessions_b2b": 0,
        "page_views": 42,
        "page_views_b2b": 0,
        "browser_sessions": 10,
        "mobile_app_sessions": 25,
        "units": 28,
        "ordered_product_sales": 557.8,
        "total_order_items": 23,
        "cvr_pct": 80.0,
        "buy_box_pct_avg": 100.0
      },
      "B0GMDM6CG2": {
        "sessions": 9,
        "sessions_b2b": 0,
        "page_views": 15,
        "page_views_b2b": 0,
        "browser_sessions": 1,
        "mobile_app_sessions": 8,
        "units": 0,
        "ordered_product_sales": 0.0,
        "total_order_items": 0,
        "cvr_pct": 0.0,
        "buy_box_pct_avg": 75.0
      }
    }
  },
  "fba_orders_detail": {
    "_data_source": "sp_api_orders",
    "_source": "SP-API: /orders/v0/orders + /orders/v0/orders/{id}/orderItems",
    "total_order_lines_7day": 14,
    "orders": [
      {
        "order_id": "112-2186036-6454606",
        "date": "2026-07-01",
        "time_utc": "20:07:13",
        "buyer": null,
        "asin": "B0DJHQVJYF",
        "product": "Paw Pure Wireless Pet Water Fountain",
        "item_subtotal": 49.99,
        "status": "Shipped",
        "type": "standalone"
      },
      {
        "order_id": "112-6995265-3297037",
        "date": "2026-07-02",
        "time_utc": "01:38:37",
        "buyer": null,
        "asin": "B0FWXJ1GKT",
        "product": "Paw Pure Replacement Filter Pack",
        "item_subtotal": 20.0,
        "status": "Shipped",
        "type": "standalone"
      },
      {
        "order_id": "113-1566500-9809829",
        "date": "2026-07-02",
        "time_utc": "02:27:32",
        "buyer": null,
        "asin": "B0DJHQVJYF",
        "product": "Paw Pure Wireless Pet Water Fountain",
        "item_subtotal": 49.99,
        "status": "Shipped",
        "type": "standalone"
      },
      {
        "order_id": "113-9057649-5048210",
        "date": "2026-07-03",
        "time_utc": "03:00:15",
        "buyer": null,
        "asin": "B0DJHQVJYF",
        "product": "Paw Pure Wireless Pet Water Fountain",
        "item_subtotal": 29.99,
        "status": "Shipped",
        "type": "standalone"
      },
      {
        "order_id": "113-0024841-4915437",
        "date": "2026-07-03",
        "time_utc": "12:00:16",
        "buyer": null,
        "asin": "B0FWXJ1GKT",
        "product": "Paw Pure Replacement Filter Pack",
        "item_subtotal": 20.0,
        "status": "Shipped",
        "type": "standalone"
      },
      {
        "order_id": "114-8509628-8923431",
        "date": "2026-07-03",
        "time_utc": "14:28:16",
        "buyer": null,
        "asin": "B0FWXJ1GKT",
        "product": "Paw Pure Replacement Filter Pack",
        "item_subtotal": 20.0,
        "status": "Shipped",
        "type": "standalone"
      },
      {
        "order_id": "114-2460397-3870649",
        "date": "2026-07-03",
        "time_utc": "16:10:20",
        "buyer": null,
        "asin": "B0DJHQVJYF",
        "product": "Paw Pure Wireless Pet Water Fountain",
        "item_subtotal": 869.71,
        "status": "Shipped",
        "type": "standalone"
      },
      {
        "order_id": "114-9192374-1438647",
        "date": "2026-07-03",
        "time_utc": "20:01:34",
        "buyer": null,
        "asin": "B0DJHQVJYF",
        "product": "Paw Pure Wireless Pet Water Fountain",
        "item_subtotal": 29.99,
        "status": "Shipped",
        "type": "standalone"
      },
      {
        "order_id": "114-3422714-4915414",
        "date": "2026-07-04",
        "time_utc": "06:17:28",
        "buyer": null,
        "asin": "B0DJHQVJYF",
        "product": "Paw Pure Wireless Pet Water Fountain",
        "item_subtotal": 29.99,
        "status": "Shipped",
        "type": "standalone"
      },
      {
        "order_id": "111-0872239-6162654",
        "date": "2026-07-04",
        "time_utc": "22:01:07",
        "buyer": null,
        "asin": "B0FWXJ1GKT",
        "product": "Paw Pure Replacement Filter Pack",
        "item_subtotal": 40.0,
        "status": "Shipped",
        "type": "standalone"
      },
      {
        "order_id": "111-3313492-1923426",
        "date": "2026-07-05",
        "time_utc": "02:59:56",
        "buyer": null,
        "asin": "B0FWXJ1GKT",
        "product": "Paw Pure Replacement Filter Pack",
        "item_subtotal": 40.0,
        "status": "Shipped",
        "type": "standalone"
      },
      {
        "order_id": "113-5556408-3118648",
        "date": "2026-07-05",
        "time_utc": "13:51:18",
        "buyer": null,
        "asin": "B0DJHQVJYF",
        "product": "Paw Pure Wireless Pet Water Fountain",
        "item_subtotal": 29.99,
        "status": "Shipped",
        "type": "standalone"
      },
      {
        "order_id": "112-5819079-0131452",
        "date": "2026-07-05",
        "time_utc": "15:07:06",
        "buyer": null,
        "asin": "B0DJHQVJYF",
        "product": "Paw Pure Wireless Pet Water Fountain",
        "item_subtotal": 29.99,
        "status": "Shipped",
        "type": "standalone"
      },
      {
        "order_id": "112-8121221-9605818",
        "date": "2026-07-06",
        "time_utc": "14:52:41",
        "buyer": null,
        "asin": "B0FWXJ1GKT",
        "product": "Paw Pure Replacement Filter Pack",
        "item_subtotal": 20.0,
        "status": "Shipped",
        "type": "standalone"
      }
    ]
  },
  "sales_today": {
    "_data_source": "sp_api_orders",
    "total_order_items_today": 0,
    "units_ordered_today": 0,
    "revenue_today": 0,
    "ad_spend_today_so_far": null,
    "_ad_note": "Today's ad spend: Ads API reports use yesterday's data (today still accumulating)."
  },
  "campaign_manager": {
    "_data_source": "sp_api_finances",
    "_note": "Ad spend from Finances API ProductAdsPaymentEventList. Per-keyword detail requires Ads API.",
    "ad_spend_7day": 183.16,
    "ad_spend_30day": 685.75,
    "impressions_7day": null,
    "clicks_7day": null,
    "ad_sales_7day": null,
    "acos_7day": null,
    "acos_percent_30day": null,
    "ad_sales_30day": null
  },
  "reviews": {
    "_data_source": "pending_api",
    "_note": "Review count not yet pulled from API; existing value carried forward manually.",
    "asin": "B0DJHQVJYF"
  },
  "fba_inventory": {
    "scraped_at": "2026-07-07T17:15:30.577346Z",
    "data_source": "sp_api",
    "_source": "SP-API: /fba/inventory/v1/summaries + /catalog/2022-04-01/items",
    "fountain": {
      "asin": "B0DJHQVJYF",
      "sku": "8V-EUFB-4UF2",
      "fba_available": 290,
      "inbound": 0,
      "reserved": 3,
      "bsr_pet_supplies": 71647,
      "bsr_subcategory": {
        "rank": 1062,
        "category": "Cat Fountains"
      },
      "_bsr_source": "SP-API Catalog (displayGroupRanks + classificationRanks)",
      "units_sold_7day": 36,
      "units_sold_30day": 52,
      "revenue_7day": 1119.64,
      "revenue_30day": 1913.98,
      "price": 49.99,
      "total_fee_per_unit": 15.5,
      "daily_velocity_7day": 5.14,
      "daily_velocity_30day": 1.73,
      "days_of_supply_est_7day": 56,
      "days_of_supply_est_30day": 167
    },
    "filters": {
      "asin": "B0FWXJ1GKT",
      "sku": "97-VFBK-LUWE",
      "fba_available": 96,
      "inbound": 0,
      "reserved": 2,
      "bsr_pet_supplies": null,
      "bsr_subcategory": {
        "rank": null,
        "category": null
      },
      "_bsr_source": "SP-API Catalog (displayGroupRanks + classificationRanks)",
      "units_sold_7day": 8,
      "units_sold_30day": 27,
      "revenue_7day": 160.0,
      "revenue_30day": 537.8,
      "price": 20.0,
      "total_fee_per_unit": 6.95,
      "daily_velocity_7day": 1.14,
      "daily_velocity_30day": 0.9,
      "days_of_supply_est_7day": 84,
      "days_of_supply_est_30day": 106
    },
    "bundle": {
      "asin": "B0GMDM6CG2",
      "sku": null,
      "fba_available": null,
      "inbound": null,
      "reserved": null,
      "bsr_pet_supplies": 373291,
      "bsr_subcategory": {
        "rank": 3669,
        "category": "Cat Fountains"
      },
      "_bsr_source": "SP-API Catalog (displayGroupRanks + classificationRanks)",
      "units_sold_7day": 0,
      "units_sold_30day": 0,
      "revenue_7day": 0.0,
      "revenue_30day": 0.0,
      "price": 64.99,
      "total_fee_per_unit": 15.25,
      "daily_velocity_7day": 0.0,
      "daily_velocity_30day": 0.0,
      "days_of_supply_est_7day": null,
      "days_of_supply_est_30day": null
    }
  },
  "amazon_choice": {
    "_data_source": "manual",
    "_note": "Amazon's Choice badge status requires manual verification (no public SP-API field)."
  },
  "pending_data_requests": [
    "Solicitations API: request-review status (ready but gated)",
    "RDT for PII: buyer names in fba_orders_detail"
  ],
  "_financials_summary": {
    "refunds_7d": 0.0,
    "refunds_30d": -53.36,
    "ads_payments_7d": -183.16,
    "ads_payments_30d": -685.75
  }
}